Metadata-Version: 2.1
Name: bake-cli-imports
Version: 0.13.0
Summary: The familar Make / Bash hybrid.
Home-page: https://github.com/kennethreitz/bake
Author: Kenneth Reitz
Author-email: me@kennethreitz.org
License: MIT
Platform: UNKNOWN
Classifier: License :: OSI Approved :: MIT License
Classifier: Programming Language :: Python
Classifier: Programming Language :: Python :: 3
Classifier: Programming Language :: Python :: 3.6
Classifier: Programming Language :: Python :: 3.7
Classifier: Programming Language :: Python :: Implementation :: CPython
Classifier: Programming Language :: Python :: Implementation :: PyPy
Requires-Python: >=3.6.0
Requires-Dist: click
Requires-Dist: delegator.py
Requires-Dist: pygments
Requires-Dist: networkx
Requires-Dist: colorama
